kebbie/__init__.py
kebbie/cmd.py
kebbie/correctors.py
kebbie/emulator.py
kebbie/gesture.py
kebbie/layout.py
kebbie/noise_model.py
kebbie/oracle.py
kebbie/scorer.py
kebbie/tokenizer.py
kebbie/utils.py
kebbie/layouts/en-US.json
kebbie-0.5.1.dist-info/LICENSE
kebbie-0.5.1.dist-info/METADATA
kebbie-0.5.1.dist-info/WHEEL
kebbie-0.5.1.dist-info/entry_points.txt
kebbie-0.5.1.dist-info/top_level.txt
kebbie-0.5.1.dist-info/RECORD
