Metadata-Version: 2.1
Name: kebbie
Version: 0.5.1
Summary: A small framework to test and compare mobile keyboards
Home-page: https://github.com/FleksySDK/kebbie
Author: Nicolas REMOND
Author-email: nicolas.remond@thingthing.co
License: UNKNOWN
Platform: UNKNOWN
Classifier: Programming Language :: Python :: 3.9
Classifier: Operating System :: OS Independent
Requires-Python: >=3.9
License-File: LICENSE
Requires-Dist: regex
Requires-Dist: datasets~=3.6
Requires-Dist: scipy~=1.12
Requires-Dist: numpy~=1.26
Requires-Dist: requests~=2.31
Requires-Dist: opencv-python~=4.9
Requires-Dist: tesseract~=0.1
Requires-Dist: pytesseract~=0.3
Requires-Dist: appium-python-client~=2.9
Provides-Extra: all
Requires-Dist: pytest~=8.0; extra == "all"
Requires-Dist: pytest-cov~=6.1; extra == "all"
Requires-Dist: pre-commit~=4.2; extra == "all"
Requires-Dist: ruff~=0.2; extra == "all"
Requires-Dist: mkdocs-material~=9.0; extra == "all"
Requires-Dist: mkdocstrings[python]~=0.18; extra == "all"
Requires-Dist: mike~=2.0; extra == "all"
Provides-Extra: dev
Requires-Dist: pytest~=8.0; extra == "dev"
Requires-Dist: pytest-cov~=6.1; extra == "dev"
Requires-Dist: pre-commit~=4.2; extra == "dev"
Requires-Dist: ruff~=0.2; extra == "dev"
Requires-Dist: mkdocs-material~=9.0; extra == "dev"
Requires-Dist: mkdocstrings[python]~=0.18; extra == "dev"
Requires-Dist: mike~=2.0; extra == "dev"
Provides-Extra: docs
Requires-Dist: mkdocs-material~=9.0; extra == "docs"
Requires-Dist: mkdocstrings[python]~=0.18; extra == "docs"
Requires-Dist: mike~=2.0; extra == "docs"
Provides-Extra: hook
Requires-Dist: pre-commit~=4.2; extra == "hook"
Provides-Extra: lint
Requires-Dist: ruff~=0.2; extra == "lint"
Provides-Extra: test
Requires-Dist: pytest~=8.0; extra == "test"
Requires-Dist: pytest-cov~=6.1; extra == "test"
